skypoint_python_cdm/ADLSPandasReader.py
skypoint_python_cdm/ADLSReader.py
skypoint_python_cdm/ADLSWriter.py
skypoint_python_cdm/Annotation.py
skypoint_python_cdm/Attribute.py
skypoint_python_cdm/AttributeReference.py
skypoint_python_cdm/Base.py
skypoint_python_cdm/CdmDataType.py
skypoint_python_cdm/CsvFormatSettings.py
skypoint_python_cdm/DataObject.py
skypoint_python_cdm/Entity.py
skypoint_python_cdm/FileFormatSettings.py
skypoint_python_cdm/JsonEnum.py
skypoint_python_cdm/LocalEntity.py
skypoint_python_cdm/MetadataObject.py
skypoint_python_cdm/Model.py
skypoint_python_cdm/ObjectCollection.py
skypoint_python_cdm/Partition.py
skypoint_python_cdm/Polymorphic.py
skypoint_python_cdm/Reader.py
skypoint_python_cdm/Reference.py
skypoint_python_cdm/ReferenceEntity.py
skypoint_python_cdm/Relationship.py
skypoint_python_cdm/S3Writer.py
skypoint_python_cdm/SchemaEntry.py
skypoint_python_cdm/SingleKeyRelationship.py
skypoint_python_cdm/Writer.py
skypoint_python_cdm/__init__.py
skypoint_python_cdm/utils.py
skypoint_python_cdm/config/config.ini
cdm_connector-0.0.6.70.dist-info/LICENSE
cdm_connector-0.0.6.70.dist-info/METADATA
cdm_connector-0.0.6.70.dist-info/WHEEL
cdm_connector-0.0.6.70.dist-info/top_level.txt
cdm_connector-0.0.6.70.dist-info/RECORD
