Metadata-Version: 2.1
Name: cdm-connector
Version: 0.0.6.70
Summary: A Python package to read and write files in CDM format. Customized for SkyPoint use cases.
Home-page: https://github.com/skypointcloud/skypoint-python-cdm-connector
Author: SkyPoint Cloud
Author-email: support@skypointcloud.com
License: GPL-3.0
Platform: UNKNOWN
Classifier: Programming Language :: Python :: 3
Classifier: License :: OSI Approved :: MIT License
Classifier: Operating System :: OS Independent
Requires-Dist: pandas (==1.0.1)
Requires-Dist: azure-storage-blob (==2.1.0)
Requires-Dist: numpy (==1.18.2)
Requires-Dist: retry (==0.9.2)
Requires-Dist: boto3 (==1.14.2)
Requires-Dist: botocore (==1.17.2)
